Workbook

Sheet Leia-me
A1: Agente Inteligente de Viagens – Modelo de custo, margem e ROI
A3: Para que serve
A4: Estimar custo variável por usuário, margem por opção de preço (passe ou assinatura), custo do piloto de 60 dias e ROI em 12 meses.
A6: Como usar
A7: 1. Edite apenas as células da aba Premissas (texto azul). Células com fundo amarelo são chutes ou escolhas suas: substitua pelos valores reais.
A8: 2. Escolha o cenário de custo (Mínimo / Base / Máximo) em Premissas!B31. Ele alimenta a aba ROI 12 meses.
A9: 3. A flexibilidade de datas (Premissas, linha 21) é a premissa que mais mexe no custo de dados de voo: cada combinação de datas é uma busca.
A11: Abas
A12: Premissas – todas as entradas do modelo.
A13: Dados de voo – nº de buscas e custo por usuário; sensibilidade por combinações de datas e por número de usuários.
A14: Margem por usuário – custo variável por componente e margem por opção de preço, comparada à meta de 30% do plano.
A15: Piloto 60 dias – custo de caixa estimado do piloto (não inclui horas da equipe).
... A28: • Horas da equipe só entram no ROI se você preencher Premissas!B28.

Sheet Premissas
A1: Premissas
A2: Edite apenas o texto azul. Fundo amarelo = chute ou campo a preencher.
A4: PREÇOS (hipóteses do plano, a validar no piloto)
A5: Passe por viagem – preço baixo | B5: 29.9 | E5: R$ | F5: Faixa do plano: R$ 29,90–49,90
A6: Passe por viagem – preço médio | B6: 39.9 | E6: R$ | F6: Ponto intermediário da faixa
A7: Passe por viagem – preço alto | B7: 49.9 | E7: R$
A8: Assinatura Pro (por mês) | B8: 24.9 | E8: R$/mês | F8: Faixa do plano: R$ 19,90–29,90/mês
A9: Comissão média de afiliados por usuário | B9: 0 | E9: R$/mês | F9: Conservador: ignora afiliados (complemento no plano)
A10: CAC por usuário (placeholder) | B10: 15 | E10: R$ | F10: Chute meu: o plano não traz hipótese de CAC. Substitua pelo valor real.
A12: DADOS DE VOO
A13: Câmbio | B13: 5.5 | E13: R$/US$ | F13: Aproximado, atualize
A14: Preço por 1.000 buscas | B14: 2 | E14: US$ | F14: Preço de lista de um provedor pay-per-use (Ignav, set/2026): US$ 2 por mil buscas após 1.000 gratuitas. Confirmar cobertura de rotas brasileiras e preço atual.
A15: Buscas gratuitas (abatidas do total) | B15: 0 | E15: buscas | F15: Provedor cita 1.000 gratuitas; não está claro se é mensal ou único. Conservador: 0. Usada só na aba Piloto.
A16: Rotas por usuário | B16: 5 | E16: rotas | F16: Exemplo usado na estimativa anterior (30 usuários x 5 rotas)
A17: Dias de consulta por mês | B17: 30 | E17: dias | F17: Consulta diária, como no plano
A18: Redução de buscas por cache e frequência adaptativa | B18: 0 | E18: % | F18: Conservador: 0%. Alavanca de custo citada no plano.
A20: CUSTO VARIÁVEL POR USUÁRIO/MÊS (cenários) | B20: Mínimo | C20: Base | D20: Máximo
A21: Combinações de datas por rota (por dia) | B21: 1 | C21: 3 | D21: 10 | E21: combinações | F21: Flexibilidade de datas: cada combinação de ida e volta é uma busca. Premissa que mais pesa.
A22: LLM (criar radar, esclarecer, explicar alertas) | B22: 1 | C22: 2 | D22: 3 | E22: R$/usuário/mês | F22: Estimativa: faixa R$ 1–3
A23: E-mail transacional | B23: 0.2 | C23: 0.35 | D23: 0.5 | E23: R$/usuário/mês | F23: Estimativa: menos de R$ 0,50
A24: Pagamento (cartão ou Pix) | B24: 1 | C24: 1.5 | D24: 2 | E24: R$/usuário/mês | F24: Estimativa: faixa R$ 1–2
A25: O custo de dados de voo por usuário é calculado na aba Dados de voo.
A26: CUSTOS FIXOS, INVESTIMENTO E METAS
A27: Custo fixo mensal | B27: 400 | E27: R$/mês | F27: Base sugerida para MVP (hospedagem, banco, automação, ferramentas)
A28: Outros investimentos iniciais (placeholder) | B28: 10000 | E28: R$ | F28: Chute meu (horas da equipe, marketing, jurídico/LGPD). Substitua pelo valor real.
A29: Meses de operação para o ROI | B29: 12 | E29: meses
A30: Meta de custo variável / receita | B30: 0.3 | E30: % | F30: Hipótese do plano: abaixo de 30%
A31: Cenário de custo selecionado | B31: Base | F31: Escolha Mínimo, Base ou Máximo. Alimenta a aba ROI 12 meses.
A33: VOLUME MENSAL (passes vendidos ou assinantes ativos) | B33: Conservador | C33: Base | D33: Otimista
A34: Volume por mês | B34: 50 | C34: 100 | D34: 200 | E34: usuários/mês | F34: Exemplo ilustrativo, substitua pela sua meta
A36: PILOTO DE 60 DIAS (cenários) | B36: Mínimo | C36: Base | D36: Máximo
A37: Usuários no piloto | B37: 15 | C37: 25 | D37: 30 | E37: usuários | F37: Plano: 15 a 30 participantes
A38: Duração do piloto | B38: 60 | C38: 60 | D38: 60 | E38: dias
A39: Hospedagem, banco e automação (total) | B39: 0 | C39: 300 | D39: 600 | E39: R$ | F39: Estimativa: planos gratuitos até R$ 140–300/mês
A40: E-mail transacional e métricas (total) | B40: 0 | C40: 0 | D40: 0 | E40: R$ | F40: Faixas gratuitas bastam, segundo a estimativa
A41: API de LLM (desenvolvimento e uso do piloto) | B41: 100 | C41: 200 | D41: 300 | E41: R$ | F41: Estimativa: R$ 100–300

Sheet Dados de voo
A1: Dados de voo – buscas e custo
A2: Custo por usuário ignora a cota gratuita (conservador). Todas as entradas vêm da aba Premissas.
A4: Item | B4: Mínimo | C4: Base | D4: Máximo
A5: Combinações de datas por rota (por dia) | B5: =Premissas!B21 -> 1 | C5: =Premissas!C21 -> 3 | D5: =Premissas!D21 -> 10
A6: Rotas por usuário | B6: =Premissas!$B$16 -> 5 | C6: =Premissas!$B$16 -> 5 | D6: =Premissas!$B$16 -> 5
A7: Dias de consulta por mês | B7: =Premissas!$B$17 -> 30 | C7: =Premissas!$B$17 -> 30 | D7: =Premissas!$B$17 -> 30
A8: Buscas por usuário/mês | B8: =B5*B6*B7*(1-Premissas!$B$18) -> 150 | C8: =C5*C6*C7*(1-Premissas!$B$18) -> 450 | D8: =D5*D6*D7*(1-Premissas!$B$18) -> 1500
A9: Custo por usuário (US$) | B9: =B8/1000*Premissas!$B$14 -> 0.3 | C9: =C8/1000*Premissas!$B$14 -> 0.9 | D9: =D8/1000*Premissas!$B$14 -> 3
A10: Custo por usuário (R$) | B10: =B9*Premissas!$B$13 -> 1.65 | C10: =C9*Premissas!$B$13 -> 4.95 | D10: =D9*Premissas!$B$13 -> 16.5
A12: Sensibilidade: custo por usuário/mês conforme a flexibilidade de datas
A13: Combinações de datas | B13: Buscas/usuário/mês | C13: Custo (R$/usuário/mês)
A14: 1 | B14: =A14*Premissas!$B$16*Premissas!$B$17*(1-Premissas!$B$18) -> 150 | C14: =B14/1000*Premissas!$B$14*Premissas!$B$13 -> 1.65
A15: 2 | B15: =A15*Premissas!$B$16*Premissas!$B$17*(1-Premissas!$B$18) -> 300 | C15: =B15/1000*Premissas!$B$14*Premissas!$B$13 -> 3.3
A16: 3 | B16: =A16*Premissas!$B$16*Premissas!$B$17*(1-Premissas!$B$18) -> 450 | C16: =B16/1000*Premissas!$B$14*Premissas!$B$13 -> 4.95
A17: 5 | B17: =A17*Premissas!$B$16*Premissas!$B$17*(1-Premissas!$B$18) -> 750 | C17: =B17/1000*Premissas!$B$14*Premissas!$B$13 -> 8.25
A18: 10 | B18: =A18*Premissas!$B$16*Premissas!$B$17*(1-Premissas!$B$18) -> 1500 | C18: =B18/1000*Premissas!$B$14*Premissas!$B$13 -> 16.5
A19: 20 | B19: =A19*Premissas!$B$16*Premissas!$B$17*(1-Premissas!$B$18) -> 3000 | C19: =B19/1000*Premissas!$B$14*Premissas!$B$13 -> 33
A22: Sensibilidade: custo mensal total de dados de voo (R$) por nº de usuários e combinações de datas
A23: Combinações \ Usuários | B23: 15 | C23: 30 | D23: 100 | E23: 200
A24: 1 | B24: =$A24*B$23*Premissas!$B$16*Premissas!$B$17*(1-Premissas!$B$18)/1000*Premissas!$B$14*Premissas!$B$13 -> 24.75 | C24: =$A24*C$23*Premissas!$B$16*Premissas!$B$17*(1-Premissas!$B$18)/1000*Premissas!$B$14*Premissas!$B$13 -> 49.5 | D24: =$A24*D$23*Premissas!$B$16*Premissas!$B$17*(1-Premissas!$B$18)/1000*Premissas!$B$14*Premissas!$B$13 -> 165 | E24: =$A24*E$23*Premissas!$B$16*Premissas!$B$17*(1-Premissas!$B$18)/1000*Premissas!$B$14*Premissas!$B$13 -> 330
A25: 3 | B25: =$A25*B$23*Premissas!$B$16*Premissas!$B$17*(1-Premissas!$B$18)/1000*Premissas!$B$14*Premissas!$B$13 -> 74.25 | C25: =$A25*C$23*Premissas!$B$16*Premissas!$B$17*(1-Premissas!$B$18)/1000*Premissas!$B$14*Premissas!$B$13 -> 148.5 | D25: =$A25*D$23*Premissas!$B$16*Premissas!$B$17*(1-Premissas!$B$18)/1000*Premissas!$B$14*Premissas!$B$13 -> 495 | E25: =$A25*E$23*Premissas!$B$16*Premissas!$B$17*(1-Premissas!$B$18)/1000*Premissas!$B$14*Premissas!$B$13 -> 990
A26: 10 | B26: =$A26*B$23*Premissas!$B$16*Premissas!$B$17*(1-Premissas!$B$18)/1000*Premissas!$B$14*Premissas!$B$13 -> 247.5 | C26: =$A26*C$23*Premissas!$B$16*Premissas!$B$17*(1-Premissas!$B$18)/1000*Premissas!$B$14*Premissas!$B$13 -> 495 | D26: =$A26*D$23*Premissas!$B$16*Premissas!$B$17*(1-Premissas!$B$18)/1000*Premissas!$B$14*Premissas!$B$13 -> 1650 | E26: =$A26*E$23*Premissas!$B$16*Premissas!$B$17*(1-Premissas!$B$18)/1000*Premissas!$B$14*Premissas!$B$13 -> 3300
A27: 20 | B27: =$A27*B$23*Premissas!$B$16*Premissas!$B$17*(1-Premissas!$B$18)/1000*Premissas!$B$14*Premissas!$B$13 -> 495 | C27: =$A27*C$23*Premissas!$B$16*Premissas!$B$17*(1-Premissas!$B$18)/1000*Premissas!$B$14*Premissas!$B$13 -> 990 | D27: =$A27*D$23*Premissas!$B$16*Premissas!$B$17*(1-Premissas!$B$18)/1000*Premissas!$B$14*Premissas!$B$13 -> 3300 | E27: =$A27*E$23*Premissas!$B$16*Premissas!$B$17*(1-Premissas!$B$18)/1000*Premissas!$B$14*Premissas!$B$13 -> 6600

Sheet Margem por usuário
A1: Margem de contribuição por usuário
A2: Margem = preço + comissão − custo variável (LLM + dados de voo + e-mail + pagamento).
A4: Custo variável (R$/usuário/mês) | B4: Mínimo | C4: Base | D4: Máximo
A5: LLM | B5: =Premissas!B22 -> 1 | C5: =Premissas!C22 -> 2 | D5: =Premissas!D22 -> 3
A6: Dados de voo | B6: ='Dados de voo'!B10 -> 1.65 | C6: ='Dados de voo'!C10 -> 4.95 | D6: ='Dados de voo'!D10 -> 16.5
A7: E-mail | B7: =Premissas!B23 -> 0.2 | C7: =Premissas!C23 -> 0.35 | D7: =Premissas!D23 -> 0.5
A8: Pagamento | B8: =Premissas!B24 -> 1 | C8: =Premissas!C24 -> 1.5 | D8: =Premissas!D24 -> 2
A9: Total | B9: =SUM(B5:B8) -> 3.85 | C9: =SUM(C5:C8) -> 8.8 | D9: =SUM(D5:D8) -> 22
A12: Opção | B12: Preço (R$) | C12: Custo var. Mínimo | D12: Custo var. Base | E12: Custo var. Máximo | F12: Margem Mínimo | G12: Margem Base | H12: Margem Máximo | I12: Custo/receita Mínimo | J12: Custo/receita Base | K12: Custo/receita Máximo | L12: Atende meta? (Base) | M12: Atende meta? (Máximo) | N12: Passes p/ pagar o CAC (Base)
A13: Passe – preço baixo | B13: =Premissas!B5 -> 29.9 | C13: =$B$9 -> 3.85 | D13: =$C$9 -> 8.8 | E13: =$D$9 -> 22 | F13: =$B13+Premissas!$B$9-C13 -> 26.05 | G13: =$B13+Premissas!$B$9-D13 -> 21.1 | H13: =$B13+Premissas!$B$9-E13 -> 7.9 | I13: =IF($B13>0,C13/$B13,0) -> 0.12876254 | J13: =IF($B13>0,D13/$B13,0) -> 0.29431438 | K13: =IF($B13>0,E13/$B13,0) -> 0.73578595 | L13: =IF(J13<=Premissas!$B$30,"Sim","Não") -> Sim | M13: =IF(K13<=Premissas!$B$30,"Sim","Não") -> Não | N13: =IF(G13>0,Premissas!$B$10/G13,"n/a") -> 0.71090047
A14: Passe – preço médio | B14: =Premissas!B6 -> 39.9 | C14: =$B$9 -> 3.85 | D14: =$C$9 -> 8.8 | E14: =$D$9 -> 22 | F14: =$B14+Premissas!$B$9-C14 -> 36.05 | G14: =$B14+Premissas!$B$9-D14 -> 31.1 | H14: =$B14+Premissas!$B$9-E14 -> 17.9 | I14: =IF($B14>0,C14/$B14,0) -> 0.096491228 | J14: =IF($B14>0,D14/$B14,0) -> 0.22055138 | K14: =IF($B14>0,E14/$B14,0) -> 0.55137845 | L14: =IF(J14<=Premissas!$B$30,"Sim","Não") -> Sim | M14: =IF(K14<=Premissas!$B$30,"Sim","Não") -> Não | N14: =IF(G14>0,Premissas!$B$10/G14,"n/a") -> 0.48231511
A15: Passe – preço alto | B15: =Premissas!B7 -> 49.9 | C15: =$B$9 -> 3.85 | D15: =$C$9 -> 8.8 | E15: =$D$9 -> 22 | F15: =$B15+Premissas!$B$9-C15 -> 46.05 | G15: =$B15+Premissas!$B$9-D15 -> 41.1 | H15: =$B15+Premissas!$B$9-E15 -> 27.9 | I15: =IF($B15>0,C15/$B15,0) -> 0.077154309 | J15: =IF($B15>0,D15/$B15,0) -> 0.17635271 | K15: =IF($B15>0,E15/$B15,0) -> 0.44088176 | L15: =IF(J15<=Premissas!$B$30,"Sim","Não") -> Sim | M15: =IF(K15<=Premissas!$B$30,"Sim","Não") -> Não | N15: =IF(G15>0,Premissas!$B$10/G15,"n/a") -> 0.3649635
A16: Assinatura Pro (mensal) | B16: =Premissas!B8 -> 24.9 | C16: =$B$9 -> 3.85 | D16: =$C$9 -> 8.8 | E16: =$D$9 -> 22 | F16: =$B16+Premissas!$B$9-C16 -> 21.05 | G16: =$B16+Premissas!$B$9-D16 -> 16.1 | H16: =$B16+Premissas!$B$9-E16 -> 2.9 | I16: =IF($B16>0,C16/$B16,0) -> 0.15461847 | J16: =IF($B16>0,D16/$B16,0) -> 0.35341365 | K16: =IF($B16>0,E16/$B16,0) -> 0.88353414 | L16: =IF(J16<=Premissas!$B$30,"Sim","Não") -> Não | M16: =IF(K16<=Premissas!$B$30,"Sim","Não") -> Não | N16: =IF(G16>0,Premissas!$B$10/G16,"n/a") -> 0.93167702
A18: Passes para pagar o CAC = CAC por usuário ÷ margem base. O CAC é um placeholder (Premissas!B10).

Sheet Piloto 60 dias
A1: Custo de caixa do piloto (60 dias)
A2: Não inclui horas da equipe. A cota gratuita de buscas (Premissas!B15) é abatida uma única vez.
A4: Item | B4: Mínimo | C4: Base | D4: Máximo
A5: Usuários no piloto | B5: =Premissas!B37 -> 15 | C5: =Premissas!C37 -> 25 | D5: =Premissas!D37 -> 30
A6: Duração (dias) | B6: =Premissas!B38 -> 60 | C6: =Premissas!C38 -> 60 | D6: =Premissas!D38 -> 60
A7: Buscas no piloto | B7: =B5*Premissas!$B$16*Premissas!B21*B6*(1-Premissas!$B$18) -> 4500 | C7: =C5*Premissas!$B$16*Premissas!C21*C6*(1-Premissas!$B$18) -> 22500 | D7: =D5*Premissas!$B$16*Premissas!D21*D6*(1-Premissas!$B$18) -> 90000
A8: Buscas faturáveis | B8: =MAX(0,B7-Premissas!$B$15) -> 4500 | C8: =MAX(0,C7-Premissas!$B$15) -> 22500 | D8: =MAX(0,D7-Premissas!$B$15) -> 90000
A9: Dados de voo (R$) | B9: =B8/1000*Premissas!$B$14*Premissas!$B$13 -> 49.5 | C9: =C8/1000*Premissas!$B$14*Premissas!$B$13 -> 247.5 | D9: =D8/1000*Premissas!$B$14*Premissas!$B$13 -> 990
A10: Hospedagem, banco e automação (R$) | B10: =Premissas!B39 -> 0 | C10: =Premissas!C39 -> 300 | D10: =Premissas!D39 -> 600
A11: E-mail e métricas (R$) | B11: =Premissas!B40 -> 0 | C11: =Premissas!C40 -> 0 | D11: =Premissas!D40 -> 0
A12: API de LLM (R$) | B12: =Premissas!B41 -> 100 | C12: =Premissas!C41 -> 200 | D12: =Premissas!D41 -> 300
A13: Total de caixa (R$) | B13: =SUM(B9:B12) -> 149.5 | C13: =SUM(C9:C12) -> 747.5 | D13: =SUM(D9:D12) -> 1890
A15: Custo de caixa por usuário do piloto (R$) | B15: =IF(B5>0,B13/B5,0) -> 9.9666667 | C15: =IF(C5>0,C13/C5,0) -> 29.9 | D15: =IF(D5>0,D13/D5,0) -> 63

Sheet ROI 12 meses
A1: ROI em 12 meses
A2: ROI = (lucro acumulado no período − investimento inicial) ÷ investimento inicial. Volume constante, sem crescimento nem churn.
A3: Cenário de custo selecionado | B3: =Premissas!B31 -> Base
A4: Custo variável por usuário (R$) | B4: =INDEX('Margem por usuário'!$B$9:$D$9,MATCH($B$3,'Margem por usuário'!$B$4:$D$4,0)) -> 8.8
A5: Custo de caixa do piloto (R$) | B5: =INDEX('Piloto 60 dias'!$B$13:$D$13,MATCH($B$3,'Piloto 60 dias'!$B$4:$D$4,0)) -> 747.5
A6: Outros investimentos iniciais (R$) | B6: =Premissas!B28 -> 10000
A7: Investimento inicial total (R$) | B7: =B5+B6 -> 10747.5
A8: Custo fixo mensal (R$) | B8: =Premissas!B27 -> 400
A9: Meses de operação | B9: =Premissas!B29 -> 12
A10: Comissão média por usuário (R$) | B10: =Premissas!B9 -> 0
D12: Volume mensal → | E12: =Premissas!B34 -> 50 | F12: =Premissas!C34 -> 100 | G12: =Premissas!D34 -> 200 | H12: =Premissas!B34 -> 50 | I12: =Premissas!C34 -> 100 | J12: =Premissas!D34 -> 200
A13: Opção | B13: Preço (R$) | C13: Margem/usuário (R$) | D13: Equilíbrio (usuários/mês) | E13: Lucro mensal – Conservador | F13: Lucro mensal – Base | G13: Lucro mensal – Otimista | H13: ROI – Conservador | I13: ROI – Base | J13: ROI – Otimista
A14: Passe – preço baixo | B14: =Premissas!B5 -> 29.9 | C14: =B14+$B$10-$B$4 -> 21.1 | D14: =IF(C14>0,$B$8/C14,"n/a") -> 18.957346 | E14: =E$12*$C14-$B$8 -> 655 | F14: =F$12*$C14-$B$8 -> 1710 | G14: =G$12*$C14-$B$8 -> 3820 | H14: =IF($B$7>0,(E14*$B$9-$B$7)/$B$7,"n/a") -> -0.26866713 | I14: =IF($B$7>0,(F14*$B$9-$B$7)/$B$7,"n/a") -> 0.90928123 | J14: =IF($B$7>0,(G14*$B$9-$B$7)/$B$7,"n/a") -> 3.2651779
A15: Passe – preço médio | B15: =Premissas!B6 -> 39.9 | C15: =B15+$B$10-$B$4 -> 31.1 | D15: =IF(C15>0,$B$8/C15,"n/a") -> 12.861736 | E15: =E$12*$C15-$B$8 -> 1155 | F15: =F$12*$C15-$B$8 -> 2710 | G15: =G$12*$C15-$B$8 -> 5820 | H15: =IF($B$7>0,(E15*$B$9-$B$7)/$B$7,"n/a") -> 0.28960223 | I15: =IF($B$7>0,(F15*$B$9-$B$7)/$B$7,"n/a") -> 2.02582 | J15: =IF($B$7>0,(G15*$B$9-$B$7)/$B$7,"n/a") -> 5.4982554
A16: Passe – preço alto | B16: =Premissas!B7 -> 49.9 | C16: =B16+$B$10-$B$4 -> 41.1 | D16: =IF(C16>0,$B$8/C16,"n/a") -> 9.7323601 | E16: =E$12*$C16-$B$8 -> 1655 | F16: =F$12*$C16-$B$8 -> 3710 | G16: =G$12*$C16-$B$8 -> 7820 | H16: =IF($B$7>0,(E16*$B$9-$B$7)/$B$7,"n/a") -> 0.8478716 | I16: =IF($B$7>0,(F16*$B$9-$B$7)/$B$7,"n/a") -> 3.1423587 | J16: =IF($B$7>0,(G16*$B$9-$B$7)/$B$7,"n/a") -> 7.7313329
A17: Assinatura Pro (mensal) | B17: =Premissas!B8 -> 24.9 | C17: =B17+$B$10-$B$4 -> 16.1 | D17: =IF(C17>0,$B$8/C17,"n/a") -> 24.84472 | E17: =E$12*$C17-$B$8 -> 405 | F17: =F$12*$C17-$B$8 -> 1210 | G17: =G$12*$C17-$B$8 -> 2820 | H17: =IF($B$7>0,(E17*$B$9-$B$7)/$B$7,"n/a") -> -0.54780181 | I17: =IF($B$7>0,(F17*$B$9-$B$7)/$B$7,"n/a") -> 0.35101186 | J17: =IF($B$7>0,(G17*$B$9-$B$7)/$B$7,"n/a") -> 2.1486392
A19: Notas:
A20: • Um passe equivale a um mês de radar ativo por usuário, e a assinatura é tratada como usuário/mês. O LTV da assinatura depende de retenção, que o modelo não captura.
A21: • Para a assinatura, o volume é o nº de assinantes ativos por mês. Para o passe, é o nº de passes vendidos por mês.
A22: • O CAC não está no ROI. Veja 'Passes p/ pagar o CAC' na aba Margem por usuário.
A23: • Mude o cenário de custo em Premissas!B31 para ver o ROI com custo mínimo ou máximo.
